{
    "Paper": "2014 Ditzfield",
    "Year": 2014,
    "Title": "Self-structure and emotional experience",
    "Authors": "Ditzfield, C.P., Showers, C.J.",
    "Journal": "Cognition and Emotion",
    "Studies": ["study1_sample1.csv"],
    "Usable": ["study1_sample1.csv"],
    "Manipulation": [],
    "Reported": {
        "study1_sample1": {
            "total": 139
        }
    },
    "Filter":{
        "study1_sample1": {
        }
    },
    "Recode":{
        "study1_sample1": {
            "RACE":{
                "race/ethn: White": 1,
                "race/ethn: Hispanic": 6,
                "race/ethn: Black": 2,
                "race/ethn: Native American": 3,
                "race/ethn: Hawaiian/Pacific Islander": 4,
                "race/ethn: Asian": 5,
                "race/ethn: Other": 7
            },
            "GENDER":{
                "M": 1,
                "F": 2
            }
        }
    },
    "Replace":{
        "study1_sample1":{
            "_NAN_": 999,
            "_NAN_": "NA",
            "_NAN_": "#NULL!"
        }
    }
}
